ros_rosidl_generator_cpp-4.9.5.data/data/lib/python3.10/site-packages/rosidl_generator_cpp/__init__.py
ros_rosidl_generator_cpp-4.9.5.data/data/lib/python3.10/site-packages/rosidl_generator_cpp/cli.py
ros_rosidl_generator_cpp-4.9.5.data/data/lib/python3.10/site-packages/rosidl_generator_cpp/__pycache__/__init__.cpython-310.pyc
ros_rosidl_generator_cpp-4.9.5.data/data/lib/python3.10/site-packages/rosidl_generator_cpp/__pycache__/cli.cpython-310.pyc
ros_rosidl_generator_cpp-4.9.5.data/data/lib/python3.10/site-packages/rosidl_generator_cpp-4.9.5-py3.10.egg-info/PKG-INFO
ros_rosidl_generator_cpp-4.9.5.data/data/lib/python3.10/site-packages/rosidl_generator_cpp-4.9.5-py3.10.egg-info/SOURCES.txt
ros_rosidl_generator_cpp-4.9.5.data/data/lib/python3.10/site-packages/rosidl_generator_cpp-4.9.5-py3.10.egg-info/dependency_links.txt
ros_rosidl_generator_cpp-4.9.5.data/data/lib/python3.10/site-packages/rosidl_generator_cpp-4.9.5-py3.10.egg-info/entry_points.txt
ros_rosidl_generator_cpp-4.9.5.data/data/lib/python3.10/site-packages/rosidl_generator_cpp-4.9.5-py3.10.egg-info/top_level.txt
ros_rosidl_generator_cpp-4.9.5.data/data/lib/rosidl_generator_cpp/rosidl_generator_cpp
ros_rosidl_generator_cpp-4.9.5.data/data/share/ament_index/resource_index/package_run_dependencies/rosidl_generator_cpp
ros_rosidl_generator_cpp-4.9.5.data/data/share/ament_index/resource_index/packages/rosidl_generator_cpp
ros_rosidl_generator_cpp-4.9.5.data/data/share/ament_index/resource_index/parent_prefix_path/rosidl_generator_cpp
ros_rosidl_generator_cpp-4.9.5.data/data/share/ament_index/resource_index/rosidl_generator_packages/rosidl_generator_cpp
ros_rosidl_generator_cpp-4.9.5.data/data/share/rosidl_generator_cpp/local_setup.bash
ros_rosidl_generator_cpp-4.9.5.data/data/share/rosidl_generator_cpp/local_setup.dsv
ros_rosidl_generator_cpp-4.9.5.data/data/share/rosidl_generator_cpp/local_setup.sh
ros_rosidl_generator_cpp-4.9.5.data/data/share/rosidl_generator_cpp/local_setup.zsh
ros_rosidl_generator_cpp-4.9.5.data/data/share/rosidl_generator_cpp/package.dsv
ros_rosidl_generator_cpp-4.9.5.data/data/share/rosidl_generator_cpp/package.xml
ros_rosidl_generator_cpp-4.9.5.data/data/share/rosidl_generator_cpp/cmake/register_cpp.cmake
ros_rosidl_generator_cpp-4.9.5.data/data/share/rosidl_generator_cpp/cmake/rosidl_generator_cpp-extras.cmake
ros_rosidl_generator_cpp-4.9.5.data/data/share/rosidl_generator_cpp/cmake/rosidl_generator_cppConfig-version.cmake
ros_rosidl_generator_cpp-4.9.5.data/data/share/rosidl_generator_cpp/cmake/rosidl_generator_cppConfig.cmake
ros_rosidl_generator_cpp-4.9.5.dist-info/METADATA
ros_rosidl_generator_cpp-4.9.5.dist-info/WHEEL
ros_rosidl_generator_cpp-4.9.5.dist-info/entry_points.txt
ros_rosidl_generator_cpp-4.9.5.dist-info/top_level.txt
ros_rosidl_generator_cpp-4.9.5.dist-info/RECORD
