Metadata-Version: 2.4
Name: ros-rosidl-generator-cpp
Version: 4.9.5
Summary: Wheel for the rosidl_generator_cpp (ros-rosidl-generator-cpp) ROS 2 package.
Requires-Dist: ros-rosidl-cmake~=4.9.5
Requires-Dist: ros-ament-index-python~=1.11.0
Requires-Dist: ros-rosidl-generator-c~=4.9.5
Requires-Dist: ros-rosidl-cli~=4.9.5
Requires-Dist: ros-rosidl-generator-type-description~=4.9.5
Requires-Dist: ros-rosidl-runtime-cpp~=4.9.5
Requires-Dist: ros-rosidl-parser~=4.9.5
Dynamic: description
Dynamic: description-content-type
Dynamic: requires-dist
Dynamic: summary
